setup.py
wayround_org/pyabber/__init__.py
wayround_org/pyabber/adhoc.py
wayround_org/pyabber/bob.py
wayround_org/pyabber/captcha.py
wayround_org/pyabber/ccc.py
wayround_org/pyabber/chat_log_widget.py
wayround_org/pyabber/chat_pager.py
wayround_org/pyabber/chat_window.py
wayround_org/pyabber/connection_window.py
wayround_org/pyabber/contact_editor.py
wayround_org/pyabber/contact_popup_menu.py
wayround_org/pyabber/disco.py
wayround_org/pyabber/icondb.py
wayround_org/pyabber/jid_widget.py
wayround_org/pyabber/l10n.py
wayround_org/pyabber/launcher.py
wayround_org/pyabber/main.py
wayround_org/pyabber/message_edit_widget.py
wayround_org/pyabber/message_filter.py
wayround_org/pyabber/message_relay.py
wayround_org/pyabber/misc.py
wayround_org/pyabber/muc.py
wayround_org/pyabber/muc_roster_storage.py
wayround_org/pyabber/muc_roster_widget.py
wayround_org/pyabber/oob.py
wayround_org/pyabber/presence_control_window.py
wayround_org/pyabber/privacy.py
wayround_org/pyabber/profile.py
wayround_org/pyabber/profile_window.py
wayround_org/pyabber/registration.py
wayround_org/pyabber/roster_storage.py
wayround_org/pyabber/roster_widget.py
wayround_org/pyabber/roster_window.py
wayround_org/pyabber/single_message_window.py
wayround_org/pyabber/status_icon.py
wayround_org/pyabber/storage.py
wayround_org/pyabber/subject_widget.py
wayround_org/pyabber/thread_widget.py
wayround_org/pyabber/xcard.py
wayround_org/pyabber/xcard_4_widgets.py
wayround_org/pyabber/xcard_temp_widgets.py
wayround_org/pyabber/xdata.py
wayround_org/pyabber/xdata_media_element.py
wayround_org/pyabber/icons/aff_admin_10x10.svg
wayround_org/pyabber/icons/aff_member_10x10.svg
wayround_org/pyabber/icons/aff_none_10x10.svg
wayround_org/pyabber/icons/aff_outcast_10x10.svg
wayround_org/pyabber/icons/aff_owner_10x10.svg
wayround_org/pyabber/icons/aff_unknown_10x10.svg
wayround_org/pyabber/icons/bye_presence.png
wayround_org/pyabber/icons/chat_presence.png
wayround_org/pyabber/icons/conn.svg
wayround_org_pyabber.egg-info/PKG-INFO
wayround_org_pyabber.egg-info/SOURCES.txt
wayround_org_pyabber.egg-info/dependency_links.txt
wayround_org_pyabber.egg-info/entry_points.txt
wayround_org_pyabber.egg-info/requires.txt
wayround_org_pyabber.egg-info/top_level.txt