Metadata-Version: 1.1
Name: wayround-org-pyabber
Version: 0.1.3
Summary: XMPP Client Implementation
Home-page: https://github.com/AnimusPEXUS/wayround_org_pyabber
Author: UNKNOWN
Author-email: UNKNOWN
License: UNKNOWN
Platform: UNKNOWN
Classifier: License :: OSI Approved :: GNU General Public License v3 or later (GPLv3+)
Classifier: Operating System :: POSIX
